{
	"requires": ["cobblemon"],
	"content": {

		"cook_rew_cobblemon_love_ball": {
			"type": "item",
			"rarity": "RARE",
			"content": "cobblemon:love_ball",
			"amount": {
			  "min": 1,
			  "max": 2
			},
			"unitWorth": 500
		},

		"cook_rew_cobblemon_premier_ball": {
			"type": "item",
			"content": "cobblemon:premier_ball",
			"amount": {
						"min": 1,
						"max": 4
			},
			"unitWorth": 250
		},

		"cook_rew_cobblemon_roseate_ball": {
			"type": "item",
			"content": "cobblemon:roseate_ball",
			"amount": {
					  "min": 1,
					  "max": 4
			},
			"unitWorth": 250
		},

		"cook_rew_cobblemon_dream_ball": {
			"type": "item",
			"rarity": "EPIC",
			"content": "cobblemon:dream_ball",
			"amount": {
			  "min": 1,
			  "max": 1
			},
			"unitWorth": 1125
		},

		"cook_rew_cobblemon_twisted_spoon": {
			"type": "item",
			"rarity": "EPIC",
			"content": "cobblemon:twisted_spoon",
			"amount": {
			  "min": 1,
			  "max": 1
			},
			"unitWorth": 4500,
			"forbids": [
				{
					"type": "item",
					"content": "cobblemon:twisted_spoon"
				}
			]
		},

        "cook_rew_cobblemon_leftovers": {
			"type": "item",
			"rarity": "LEGENDARY",
			"content": "cobblemon:leftovers",
			"amount": {
				"min": 1,
				"max": 1
			},
			"unitWorth": 4000
		},

		"cook_rew_cobblemon_lucky_egg": {
			"type": "item",
			"rarity": "LEGENDARY",
			"content": "cobblemon:lucky_egg",
			"amount": {
				"min": 1,
				"max": 1
			},
			"unitWorth": 4000
		}

	}

}